sermonaudio/__init__.py
sermonaudio/models.py
sermonaudio/utils.py
sermonaudio/broadcaster/__init__.py
sermonaudio/broadcaster/requests.py
sermonaudio/node/__init__.py
sermonaudio/node/requests.py
sermonaudio/user/__init__.py
sermonaudio/user/requests.py
sermonaudio-6.15.2.dist-info/METADATA
sermonaudio-6.15.2.dist-info/WHEEL
sermonaudio-6.15.2.dist-info/top_level.txt
sermonaudio-6.15.2.dist-info/RECORD
