Metadata-Version: 2.1
Name: sermonaudio
Version: 6.15.2
Summary: The official Python client library for accessing the SermonAudio.com APIs
Home-page: http://api.sermonaudio.com/
Author: SermonAudio.com
Author-email: info@sermonaudio.com
License: MIT
Keywords: sermon audio sermonaudio API preaching church bible
Classifier: Development Status :: 5 - Production/Stable
Classifier: Intended Audience :: Developers
Classifier: License :: OSI Approved :: MIT License
Classifier: Programming Language :: Python :: 3.6
Requires-Dist: requests >=2.19.1
Requires-Dist: pytz >=2018.5
Requires-Dist: osis-book-tools >=1.0.1
